ntfy_synologychat.py
ntfy_synologychat-0.2.0.dist-info/LICENSE
ntfy_synologychat-0.2.0.dist-info/WHEEL
ntfy_synologychat-0.2.0.dist-info/METADATA
ntfy_synologychat-0.2.0.dist-info/RECORD
